neon_mana_utils/__init__.py
neon_mana_utils/bus_api.py
neon_mana_utils/cli.py
neon_mana_utils/config.py
neon_mana_utils/constants.py
neon_mana_utils/core_commands.py
neon_mana_utils/messagebus.py
neon_mana_utils/skills.py
neon_mana_utils/status.py
neon_mana_utils/version.py
neon_mana_utils-0.3.1.dist-info/LICENSE.md
neon_mana_utils-0.3.1.dist-info/METADATA
neon_mana_utils-0.3.1.dist-info/WHEEL
neon_mana_utils-0.3.1.dist-info/entry_points.txt
neon_mana_utils-0.3.1.dist-info/top_level.txt
neon_mana_utils-0.3.1.dist-info/RECORD
