Metadata-Version: 2.1
Name: neon-mana-utils
Version: 0.3.1
Summary: Message Application for Neon AI
Home-page: https://github.com/neongeckocom/neon-mana-utils
Author: Neongecko
Author-email: developers@neon.ai
License: BSD-3-Clause
Classifier: Programming Language :: Python :: 3
Classifier: Operating System :: OS Independent
Requires-Python: >=3.6
License-File: LICENSE.md
Requires-Dist: click~=8.0
Requires-Dist: click-default-group~=1.2
Requires-Dist: mycroft-messagebus-client~=0.10
Requires-Dist: pyyaml<7.0,>=5.4
Requires-Dist: neon-utils~=1.0
Requires-Dist: ovos-utils>=0.0.20,~=0.0
